linklinux_init/__init__.py
linklinux_init/main.py
linklinux_init-1.2.0.dist-info/LICENSE
linklinux_init-1.2.0.dist-info/METADATA
linklinux_init-1.2.0.dist-info/WHEEL
linklinux_init-1.2.0.dist-info/entry_points.txt
linklinux_init-1.2.0.dist-info/top_level.txt
linklinux_init-1.2.0.dist-info/RECORD
