Metadata-Version: 2.1
Name: linklinux-init
Version: 1.2.0
Summary: A tool to configure initial development environment on Linux
Home-page: https://github.com/suyelu/LinkLinux_Init
Author: Vincnent Su
Author-email: suyelu@hotmail.com
License: UNKNOWN
Platform: UNKNOWN
Classifier: Development Status :: 4 - Beta
Classifier: Intended Audience :: Developers
Classifier: License :: OSI Approved :: MIT License
Classifier: Programming Language :: Python :: 3
Classifier: Programming Language :: Python :: 3.8
License-File: LICENSE
